respect_validation/Factory.py
respect_validation/FormValidator.py
respect_validation/Validator.py
respect_validation/__init__.py
respect_validation/py.typed
respect_validation/Exceptions/AllOfException.py
respect_validation/Exceptions/AlnumException.py
respect_validation/Exceptions/AlphaException.py
respect_validation/Exceptions/AlwaysInvalidException.py
respect_validation/Exceptions/AlwaysValidException.py
respect_validation/Exceptions/AnyOfException.py
respect_validation/Exceptions/AttributeException.py
respect_validation/Exceptions/Base64Exception.py
respect_validation/Exceptions/BaseNumException.py
respect_validation/Exceptions/BetweenException.py
respect_validation/Exceptions/BoolTypeException.py
respect_validation/Exceptions/BoolValException.py
respect_validation/Exceptions/BsnException.py
respect_validation/Exceptions/BytearrayTypeException.py
respect_validation/Exceptions/BytesTypeException.py
respect_validation/Exceptions/CallException.py
respect_validation/Exceptions/CallableTypeException.py
respect_validation/Exceptions/CallbackException.py
respect_validation/Exceptions/CharsetException.py
respect_validation/Exceptions/CnhException.py
respect_validation/Exceptions/CnpjException.py
respect_validation/Exceptions/ComponentException.py
respect_validation/Exceptions/ConsonantException.py
respect_validation/Exceptions/ContainsAnyException.py
respect_validation/Exceptions/ContainsException.py
respect_validation/Exceptions/ControlException.py
respect_validation/Exceptions/CountableException.py
respect_validation/Exceptions/CountryCodeException.py
respect_validation/Exceptions/CpfException.py
respect_validation/Exceptions/CreditCardException.py
respect_validation/Exceptions/CurrencyCodeException.py
respect_validation/Exceptions/DateException.py
respect_validation/Exceptions/DateTimeException.py
respect_validation/Exceptions/DecimalException.py
respect_validation/Exceptions/DictTypeException.py
respect_validation/Exceptions/DigitException.py
respect_validation-1.3.0.dist-info/LICENSE
respect_validation-1.3.0.dist-info/METADATA
respect_validation-1.3.0.dist-info/WHEEL
respect_validation-1.3.0.dist-info/top_level.txt
respect_validation-1.3.0.dist-info/RECORD
