Metadata-Version: 2.1
Name: respect-validation
Version: 1.3.0
Summary: Python version of "the most awesome validation engine for PHP"
Home-page: https://github.com/gurkin33/respect_validation
Author: Alexey Mochalin
Author-email: amochalini@gmail.com
License: MIT
Platform: unix
Platform: linux
Platform: osx
Platform: cygwin
Platform: win32
Classifier: License :: OSI Approved :: MIT License
Classifier: Operating System :: OS Independent
Classifier: Programming Language :: Python
Classifier: Programming Language :: Python :: 3.7
Classifier: Programming Language :: Python :: 3.8
Classifier: Programming Language :: Python :: 3.9
Classifier: Programming Language :: Python :: 3.10
Classifier: Topic :: Internet :: WWW/HTTP :: Dynamic Content
Classifier: Topic :: Software Development :: Libraries :: Python Modules
Requires-Python: >=3.7
License-File: LICENSE
Requires-Dist: chardet
Requires-Dist: pycountry
Requires-Dist: phonenumbers
Provides-Extra: testing
Requires-Dist: pytest ; extra == 'testing'
Requires-Dist: pytest-cov ; extra == 'testing'
Requires-Dist: coverage ; extra == 'testing'
Requires-Dist: tox ; extra == 'testing'
Requires-Dist: flake8 ; extra == 'testing'
